webdriver_update_tool/__init__.py
webdriver_update_tool/config.ini
webdriver_update_tool/update_chromedriver4mac.py
webdriver_update_tool-0.1.3.dist-info/LICENSE
webdriver_update_tool-0.1.3.dist-info/METADATA
webdriver_update_tool-0.1.3.dist-info/WHEEL
webdriver_update_tool-0.1.3.dist-info/top_level.txt
webdriver_update_tool-0.1.3.dist-info/RECORD
