Metadata-Version: 2.1
Name: webdriver-update-tool
Version: 0.1.3
Summary: A tool for updating the webdriver automatically
Home-page: UNKNOWN
Author: cjz25
License: UNKNOWN
Platform: UNKNOWN
Classifier: Programming Language :: Python :: 3.5
Classifier: License :: OSI Approved :: MIT License
Classifier: Operating System :: MacOS :: MacOS X
Requires-Python: >=3.5
Requires-Dist: selenium (>=3.141.0)
